pdb_openai/__init__.py
pdb_openai/debug.py
pdb_openai-0.0.8.dist-info/LICENSE
pdb_openai-0.0.8.dist-info/METADATA
pdb_openai-0.0.8.dist-info/WHEEL
pdb_openai-0.0.8.dist-info/top_level.txt
pdb_openai-0.0.8.dist-info/RECORD
