Metadata-Version: 2.1
Name: pdb-openai
Version: 0.0.8
Summary: A python debugger with OpenAI integrations
Home-page: https://github.com/dustmason/pdb_openai
Author: Jordan Sitkin
Author-email: jordan@fiftyfootfoghorn.com
License: UNKNOWN
Platform: UNKNOWN
Classifier: Programming Language :: Python :: 3
Classifier: License :: OSI Approved :: MIT License
Classifier: Operating System :: OS Independent
Requires-Python: >=3.6
License-File: LICENSE
Requires-Dist: openai
